eosdis_store/__init__.py
eosdis_store/dmrpp.py
eosdis_store/stores.py
eosdis_store/version.py
zarr_eosdis_store-0.1.6.dist-info/LICENSE
zarr_eosdis_store-0.1.6.dist-info/METADATA
zarr_eosdis_store-0.1.6.dist-info/WHEEL
zarr_eosdis_store-0.1.6.dist-info/top_level.txt
zarr_eosdis_store-0.1.6.dist-info/RECORD
