Metadata-Version: 2.1
Name: zarr-eosdis-store
Version: 0.1.6
Summary: Zarr Store class for working with EOSDIS cloud data
Home-page: https://github.com/nasa/zarr-eosdis-store
Author: Patrick Quinn, Matthew Hanson
Author-email: patrick@patrickquinn.net
Classifier: Development Status :: 7 - Inactive
Classifier: Intended Audience :: Developers
Classifier: Intended Audience :: Science/Research
Classifier: License :: OSI Approved :: Apache Software License
Classifier: Programming Language :: Python :: 3
Classifier: Programming Language :: Python :: 3.8
Classifier: Programming Language :: Python :: 3 :: Only
Requires-Python: >=3.8
License-File: LICENSE
Requires-Dist: CacheControl>=0.12.6
Requires-Dist: requests>=2.23.0
Requires-Dist: requests-futures>=1.0.0
Requires-Dist: zarr>=2.7.1
Requires-Dist: ipypb~=0.5
Requires-Dist: xarray>=0.16
Requires-Dist: numcodecs>=0.8.1
Provides-Extra: dev
Requires-Dist: setuptools>=21.0.0; extra == "dev"
Requires-Dist: pytest~=5.4; extra == "dev"
Requires-Dist: flake8~=3.8; extra == "dev"
Requires-Dist: safety>=1.8.5; extra == "dev"
Requires-Dist: coverage>=4.5.4; extra == "dev"
Requires-Dist: pygments~=2.9; extra == "dev"
Requires-Dist: sphinx>=3.2.1; extra == "dev"
Requires-Dist: sphinx-rtd-theme>=0.5.0; extra == "dev"
Requires-Dist: recommonmark>=0.7.1; extra == "dev"
